odoo/addons/l10n_es_aeat_mod390_oss/README.rst
odoo/addons/l10n_es_aeat_mod390_oss/__init__.py
odoo/addons/l10n_es_aeat_mod390_oss/__manifest__.py
odoo/addons/l10n_es_aeat_mod390_oss/data/aeat_export_mod390_sub06_data.xml
odoo/addons/l10n_es_aeat_mod390_oss/data/l10n.es.aeat.map.tax.line.csv
odoo/addons/l10n_es_aeat_mod390_oss/data/2024/l10n.es.aeat.map.tax.line.csv
odoo/addons/l10n_es_aeat_mod390_oss/i18n/l10n_es_aeat_mod390_oss.pot
odoo/addons/l10n_es_aeat_mod390_oss/models/__init__.py
odoo/addons/l10n_es_aeat_mod390_oss/models/l10n_es_aeat_map_tax_line.py
odoo/addons/l10n_es_aeat_mod390_oss/readme/CONTRIBUTORS.md
odoo/addons/l10n_es_aeat_mod390_oss/readme/DESCRIPTION.md
odoo/addons/l10n_es_aeat_mod390_oss/readme/ROADMAP.md
odoo/addons/l10n_es_aeat_mod390_oss/static/description/icon.png
odoo/addons/l10n_es_aeat_mod390_oss/static/description/icon.svg
odoo/addons/l10n_es_aeat_mod390_oss/static/description/index.html
odoo/addons/l10n_es_aeat_mod390_oss/tests/__init__.py
odoo/addons/l10n_es_aeat_mod390_oss/tests/test_l10n_es_aeat_mod390_oss.py
odoo_addon_l10n_es_aeat_mod390_oss-18.0.1.0.0.2.dist-info/METADATA
odoo_addon_l10n_es_aeat_mod390_oss-18.0.1.0.0.2.dist-info/WHEEL
odoo_addon_l10n_es_aeat_mod390_oss-18.0.1.0.0.2.dist-info/top_level.txt
odoo_addon_l10n_es_aeat_mod390_oss-18.0.1.0.0.2.dist-info/RECORD
